zwocr/__init__.py
zwocr/__version__.py
zwocr/cmd.py
zwocr/image.py
zwocr/paddle.py
zwocr-0.0.6.dist-info/LICENSE
zwocr-0.0.6.dist-info/METADATA
zwocr-0.0.6.dist-info/WHEEL
zwocr-0.0.6.dist-info/top_level.txt
zwocr-0.0.6.dist-info/RECORD
